pdj_sitegen/__init__.py
pdj_sitegen/__main__.py
pdj_sitegen/build.py
pdj_sitegen/config.py
pdj_sitegen/consts.py
pdj_sitegen/exceptions.py
pdj_sitegen/install_pandoc.py
pdj_sitegen/py.typed
pdj_sitegen/setup_site.py
pdj_sitegen/data/config.yml
pdj_sitegen/data/default.html.jinja2
pdj_sitegen/data/index.md
pdj_sitegen/data/style.css
pdj_sitegen/data/syntax.css
pdj_sitegen/filters/__init__.py
pdj_sitegen/filters/csv_code_table.py
pdj_sitegen/filters/links_md2html.py
pdj_sitegen/data/config.yml
pdj_sitegen/data/default.html.jinja2
pdj_sitegen/data/index.md
pdj_sitegen/data/style.css
pdj_sitegen/data/syntax.css
pdj_sitegen-0.0.2.dist-info/METADATA
pdj_sitegen-0.0.2.dist-info/WHEEL
pdj_sitegen-0.0.2.dist-info/licenses/LICENSE
pdj_sitegen-0.0.2.dist-info/RECORD
