Metadata-Version: 2.3
Name: pdj_sitegen
Version: 0.0.2
Summary: static site generator built on pandoc + jinja2
Project-URL: Repository, https://github.com/mivanit/pdj-sitegen
Project-URL: Issues, https://github.com/mivanit/pdj-sitegen/issues
Project-URL: Documentation, https://miv.name/pdj-sitegen/
Author-email: Michael Ivanitskiy <mivanits@umich.edu>
License-File: LICENSE
Classifier: Development Status :: 3 - Alpha
Classifier: License :: OSI Approved :: GNU General Public License v3 (GPLv3)
Classifier: Operating System :: OS Independent
Classifier: Programming Language :: Python :: 3.11
Classifier: Programming Language :: Python :: 3.12
Classifier: Topic :: Internet
Classifier: Typing :: Typed
Requires-Python: >=3.11
Requires-Dist: beautifulsoup4>=4.12.3
Requires-Dist: jinja2>=3.1.4
Requires-Dist: muutils>=0.6.15
Requires-Dist: pandocfilters>=1.5.1
Requires-Dist: pypandoc>=1.14
Requires-Dist: pyyaml>=6.0.2
Requires-Dist: tqdm>=4.66.5
